{
    "_metadata_": {
        "version": "1.0",
        "output_tag": "==done==",
        "save_figs": true,
        "description": "Full profile for GPU",
        "host": "r10i3n4",
        "profile": "./ci/full_gpu.yml",
        "start": "10/02/21 09:08:04",
        "end": "10/02/21 12:11:52",
        "duration": "3:03:48"
    },
    "LINR1": {
        "id": "LINR1",
        "dir": "LinearReg",
        "src": "01-Linear-Regression.ipynb",
        "out": "01-Linear-Regression==done==.ipynb",
        "start": "10/02/21 09:08:04",
        "end": "10/02/21 09:08:50",
        "duration": "0:00:45",
        "state": "ok"
    },
    "GRAD1": {
        "id": "GRAD1",
        "dir": "LinearReg",
        "src": "02-Gradient-descent.ipynb",
        "out": "02-Gradient-descent==done==.ipynb",
        "start": "10/02/21 09:08:50",
        "end": "10/02/21 09:09:00",
        "duration": "0:00:10",
        "state": "ok"
    },
    "POLR1": {
        "id": "POLR1",
        "dir": "LinearReg",
        "src": "03-Polynomial-Regression.ipynb",
        "out": "03-Polynomial-Regression==done==.ipynb",
        "start": "10/02/21 09:09:00",
        "end": "10/02/21 09:09:07",
        "duration": "0:00:07",
        "state": "ok"
    },
    "LOGR1": {
        "id": "LOGR1",
        "dir": "LinearReg",
        "src": "04-Logistic-Regression.ipynb",
        "out": "04-Logistic-Regression==done==.ipynb",
        "start": "10/02/21 09:09:07",
        "end": "10/02/21 09:09:14",
        "duration": "0:00:07",
        "state": "ok"
    },
    "PER57": {
        "id": "PER57",
        "dir": "IRIS",
        "src": "01-Simple-Perceptron.ipynb",
        "out": "01-Simple-Perceptron==done==.ipynb",
        "start": "10/02/21 09:09:14",
        "end": "10/02/21 09:09:20",
        "duration": "0:00:06",
        "state": "ok"
    },
    "BHPD1": {
        "id": "BHPD1",
        "dir": "BHPD",
        "src": "01-DNN-Regression.ipynb",
        "out": "01-DNN-Regression==done==.ipynb",
        "start": "10/02/21 09:09:20",
        "end": "10/02/21 09:09:37",
        "duration": "0:00:16",
        "state": "ok"
    },
    "BHPD2": {
        "id": "BHPD2",
        "dir": "BHPD",
        "src": "02-DNN-Regression-Premium.ipynb",
        "out": "02-DNN-Regression-Premium==done==.ipynb",
        "start": "10/02/21 09:09:37",
        "end": "10/02/21 09:10:01",
        "duration": "0:00:23",
        "state": "ok"
    },
    "MNIST1": {
        "id": "MNIST1",
        "dir": "MNIST",
        "src": "01-DNN-MNIST.ipynb",
        "out": "01-DNN-MNIST==done==.ipynb",
        "start": "10/02/21 09:10:01",
        "end": "10/02/21 09:10:48",
        "duration": "0:00:47",
        "state": "ok"
    },
    "MNIST2": {
        "id": "MNIST2",
        "dir": "MNIST",
        "src": "02-CNN-MNIST.ipynb",
        "out": "02-CNN-MNIST==done==.ipynb",
        "start": "10/02/21 09:10:48",
        "end": "10/02/21 09:11:46",
        "duration": "0:00:58",
        "state": "ok"
    },
    "GTSRB1": {
        "id": "GTSRB1",
        "dir": "GTSRB",
        "src": "01-Preparation-of-data.ipynb",
        "out": "01-Preparation-of-data==done==.ipynb",
        "start": "10/02/21 09:11:47",
        "end": "10/02/21 09:16:46",
        "duration": "0:04:59",
        "state": "ok"
    },
    "GTSRB2": {
        "id": "GTSRB2",
        "dir": "GTSRB",
        "src": "02-First-convolutions.ipynb",
        "out": "02-First-convolutions==done==.ipynb",
        "start": "10/02/21 09:16:47",
        "end": "10/02/21 09:17:15",
        "duration": "0:00:27",
        "state": "ok"
    },
    "GTSRB3": {
        "id": "GTSRB3",
        "dir": "GTSRB",
        "src": "03-Tracking-and-visualizing.ipynb",
        "out": "03-Tracking-and-visualizing==done==.ipynb",
        "start": "10/02/21 09:17:15",
        "end": "10/02/21 09:18:19",
        "duration": "0:01:03",
        "state": "ok"
    },
    "GTSRB4": {
        "id": "GTSRB4",
        "dir": "GTSRB",
        "src": "04-Data-augmentation.ipynb",
        "out": "04-Data-augmentation==done==.ipynb",
        "start": "10/02/21 09:18:19",
        "end": "10/02/21 09:19:57",
        "duration": "0:01:38",
        "state": "ok"
    },
    "GTSRB5_r1": {
        "id": "GTSRB5",
        "dir": "GTSRB",
        "src": "05-Full-convolutions.ipynb",
        "out": "05-Full-convolutions=1==done==.ipynb",
        "start": "10/02/21 09:19:57",
        "end": "10/02/21 09:50:47",
        "duration": "0:30:50",
        "state": "ok"
    },
    "GTSRB5_r2": {
        "id": "GTSRB5",
        "dir": "GTSRB",
        "src": "05-Full-convolutions.ipynb",
        "out": "05-Full-convolutions=2==done==.ipynb",
        "start": "10/02/21 09:50:48",
        "end": "10/02/21 10:22:00",
        "duration": "0:31:12",
        "state": "ok"
    },
    "GTSRB5_r3": {
        "id": "GTSRB5",
        "dir": "GTSRB",
        "src": "05-Full-convolutions.ipynb",
        "out": "05-Full-convolutions=3==done==.ipynb",
        "start": "10/02/21 10:22:00",
        "end": "10/02/21 10:46:34",
        "duration": "0:24:34",
        "state": "ok"
    },
    "GTSRB6": {
        "id": "GTSRB6",
        "dir": "GTSRB",
        "src": "06-Notebook-as-a-batch.ipynb",
        "out": "06-Notebook-as-a-batch==done==.ipynb",
        "start": "10/02/21 10:46:35",
        "end": "10/02/21 10:46:39",
        "duration": "0:00:04",
        "state": "ok"
    },
    "GTSRB7": {
        "id": "GTSRB7",
        "dir": "GTSRB",
        "src": "07-Show-report.ipynb",
        "out": "07-Show-report==done==.ipynb",
        "start": "10/02/21 10:46:39",
        "end": "10/02/21 10:46:43",
        "duration": "0:00:04",
        "state": "ok"
    },
    "IMDB1": {
        "id": "IMDB1",
        "dir": "IMDB",
        "src": "01-Embedding-Keras.ipynb",
        "out": "01-Embedding-Keras==done==.ipynb",
        "start": "10/02/21 10:46:43",
        "end": "10/02/21 10:47:33",
        "duration": "0:00:50",
        "state": "ok"
    },
    "IMDB2": {
        "id": "IMDB1",
        "dir": "IMDB",
        "src": "02-Prediction.ipynb",
        "out": "02-Prediction==done==.ipynb",
        "start": "10/02/21 10:47:34",
        "end": "10/02/21 10:47:39",
        "duration": "0:00:05",
        "state": "ok"
    },
    "IMDB3": {
        "id": "IMDB1",
        "dir": "IMDB",
        "src": "03-LSTM-Keras.ipynb",
        "out": "03-LSTM-Keras==done==.ipynb",
        "start": "10/02/21 10:47:39",
        "end": "10/02/21 10:55:17",
        "duration": "0:07:38",
        "state": "ok"
    },
    "SYNOP1": {
        "id": "SYNOP1",
        "dir": "SYNOP",
        "src": "01-Preparation-of-data.ipynb",
        "out": "01-Preparation-of-data==done==.ipynb",
        "start": "10/02/21 10:55:17",
        "end": "10/02/21 10:55:27",
        "duration": "0:00:09",
        "state": "ok"
    },
    "SYNOP2": {
        "id": "SYNOP2",
        "dir": "SYNOP",
        "src": "02-First-predictions.ipynb",
        "out": "02-First-predictions==done==.ipynb",
        "start": "10/02/21 10:55:27",
        "end": "10/02/21 10:57:40",
        "duration": "0:02:13",
        "state": "ok"
    },
    "SYNOP3": {
        "id": "SYNOP3",
        "dir": "SYNOP",
        "src": "03-12h-predictions.ipynb",
        "out": "03-12h-predictions==done==.ipynb",
        "start": "10/02/21 10:57:41",
        "end": "10/02/21 10:57:52",
        "duration": "0:00:10",
        "state": "ok"
    },
    "AE1": {
        "id": "AE1",
        "dir": "AE",
        "src": "01-AE-with-MNIST.ipynb",
        "out": "01-AE-with-MNIST==done==.ipynb",
        "start": "10/02/21 10:57:52",
        "end": "10/02/21 11:00:08",
        "duration": "0:02:16",
        "state": "ok"
    },
    "AE2": {
        "id": "AE2",
        "dir": "AE",
        "src": "02-AE-with-MNIST-post.ipynb",
        "out": "02-AE-with-MNIST-post==done==.ipynb",
        "start": "10/02/21 11:00:09",
        "end": "10/02/21 11:00:20",
        "duration": "0:00:11",
        "state": "ok"
    },
    "VAE1": {
        "id": "VAE1",
        "dir": "VAE",
        "src": "01-VAE-with-MNIST.ipynb",
        "out": "01-VAE-with-MNIST==done==.ipynb",
        "start": "10/02/21 11:00:20",
        "end": "10/02/21 11:01:39",
        "duration": "0:01:19",
        "state": "ok"
    },
    "VAE2": {
        "id": "VAE2",
        "dir": "VAE",
        "src": "02-VAE-with-MNIST-post.ipynb",
        "out": "02-VAE-with-MNIST-post==done==.ipynb",
        "start": "10/02/21 11:01:40",
        "end": "10/02/21 11:02:36",
        "duration": "0:00:56",
        "state": "ok"
    },
    "VAE5": {
        "id": "VAE5",
        "dir": "VAE",
        "src": "05-About-CelebA.ipynb",
        "out": "05-About-CelebA==done==.ipynb",
        "start": "10/02/21 11:02:36",
        "end": "10/02/21 11:03:06",
        "duration": "0:00:29",
        "state": "ok"
    },
    "VAE6": {
        "id": "VAE6",
        "dir": "VAE",
        "src": "06-Prepare-CelebA-datasets.ipynb",
        "out": "06-Prepare-CelebA-datasets==done==.ipynb",
        "start": "10/02/21 11:03:06",
        "end": "10/02/21 11:04:39",
        "duration": "0:01:33",
        "state": "ok"
    },
    "VAE7": {
        "id": "VAE7",
        "dir": "VAE",
        "src": "07-Check-CelebA.ipynb",
        "out": "07-Check-CelebA==done==.ipynb",
        "start": "10/02/21 11:04:39",
        "end": "10/02/21 11:06:33",
        "duration": "0:01:54",
        "state": "ok"
    },
    "VAE8": {
        "id": "VAE8",
        "dir": "VAE",
        "src": "08-VAE-with-CelebA.ipynb",
        "out": "08-VAE-with-CelebA==done==.ipynb",
        "start": "10/02/21 11:06:33",
        "end": "10/02/21 12:09:05",
        "duration": "1:02:31",
        "state": "ok"
    },
    "VAE9": {
        "id": "VAE9",
        "dir": "VAE",
        "src": "09-VAE-with-CelebA-post.ipynb",
        "out": "09-VAE-with-CelebA-post==done==.ipynb",
        "start": "10/02/21 12:09:17",
        "end": "10/02/21 12:11:21",
        "duration": "0:02:03",
        "state": "ok"
    },
    "ACTF1": {
        "id": "ACTF1",
        "dir": "Misc",
        "src": "Activation-Functions.ipynb",
        "out": "Activation-Functions==done==.ipynb",
        "start": "10/02/21 12:11:21",
        "end": "10/02/21 12:11:50",
        "duration": "0:00:29",
        "state": "ok"
    },
    "NP1": {
        "id": "NP1",
        "dir": "Misc",
        "src": "Numpy.ipynb",
        "out": "Numpy==done==.ipynb",
        "start": "10/02/21 12:11:50",
        "end": "10/02/21 12:11:51",
        "duration": "0:00:01",
        "state": "ok"
    },
    "TSB1": {
        "id": "TSB1",
        "dir": "Misc",
        "src": "Using-Tensorboard.ipynb",
        "out": "Using-Tensorboard==done==.ipynb",
        "start": "10/02/21 12:11:51",
        "end": "10/02/21 12:11:52",
        "duration": "0:00:00",
        "state": "ok"
    }
}